LICENSE
README.md
pyproject.toml
src/bed/__init__.py
src/bed/document.py
src/bed/editor.py
src/bed/element.py
src/bed/frame.py
src/bed/group.py
src/bed/helpers.py
src/bed/highlighter.py
src/bed/painter.py
src/bed/parsing.py
src/bed/settings.py
src/bed/undo.py
src/bed/icons/application-exit.svg
src/bed/icons/bed.svg
src/bed/icons/dialog-cancel.svg
src/bed/icons/document-edit.svg
src/bed/icons/document-new.svg
src/bed/icons/document-open.svg
src/bed/icons/document-save-as-template.svg
src/bed/icons/document-save-as.svg
src/bed/icons/document-save.svg
src/bed/icons/draw-line.svg
src/bed/icons/draw-triangle.svg
src/bed/icons/edit-copy.svg
src/bed/icons/edit-cut.svg
src/bed/icons/edit-delete.svg
src/bed/icons/edit-paste.svg
src/bed/icons/edit-redo.svg
src/bed/icons/edit-select-all.svg
src/bed/icons/edit-undo.svg
src/bed/icons/format-border-set-all.svg
src/bed/icons/go-bottom.svg
src/bed/icons/go-down.svg
src/bed/icons/go-next.svg
src/bed/icons/go-previous.svg
src/bed/icons/go-top.svg
src/bed/icons/go-up.svg
src/bed/icons/grid-rectangular.svg
src/bed/icons/insert-image.svg
src/bed/icons/insert-text-frame.svg
src/bed/icons/object-group.svg
src/bed/icons/object-ungroup.svg
src/bed/icons/project-development-delete-template.svg
src/bed/icons/project-development-new-template.svg
src/bed/icons/show-menu.svg
src/bed/icons/story-editor.svg
src/bed/icons/view-preview.svg
src/bed/icons/view-refresh.svg
src/bed/icons/visibility.svg
src/bed/icons/window-new.svg
src/bed/latex/bed.sty
src/bed/launcher/bed.desktop
src/bed/translation/fr.qm
src/bed_latex.egg-info/PKG-INFO
src/bed_latex.egg-info/SOURCES.txt
src/bed_latex.egg-info/dependency_links.txt
src/bed_latex.egg-info/entry_points.txt
src/bed_latex.egg-info/requires.txt
src/bed_latex.egg-info/top_level.txt