Metadata-Version: 2.1
Name: bed-latex
Version: 2.0.3
Summary: BEd: Beamer Editor, GUI for LaTeX Beamer presentations.
Author-email: Jean-Baptiste Delisle <jb.delisle@pi314.noho.st>
Project-URL: Homepage, https://framagit.org/delisle/bed
Project-URL: Issues, https://framagit.org/delisle/bed/-/issues
Classifier: Programming Language :: Python :: 3
Classifier: License :: OSI Approved :: GNU General Public License v3 or later (GPLv3+)
Classifier: Operating System :: OS Independent
Requires-Python: >=3.8
License-File: LICENSE
Requires-Dist: pyside6
Requires-Dist: pymupdf
